voxgan/__init__.py
voxgan/data/__init__.py
voxgan/data/datasets.py
voxgan/data/fluvdeposet.py
voxgan/models/__init__.py
voxgan/models/base.py
voxgan/models/dcgan.py
voxgan/models/dragan.py
voxgan/models/loss.py
voxgan/models/metrics.py
voxgan/models/mhgan.py
voxgan/models/wgan.py
voxgan/networks/__init__.py
voxgan/networks/base.py
voxgan/networks/blocks.py
voxgan/networks/dcgan.py
voxgan/networks/resnet.py
voxgan/networks/utils.py
voxgan-0.0.2.dist-info/licenses/LICENSE
voxgan-0.0.2.dist-info/METADATA
voxgan-0.0.2.dist-info/WHEEL
voxgan-0.0.2.dist-info/top_level.txt
voxgan-0.0.2.dist-info/RECORD
