Metadata-Version: 2.4
Name: voxgan
Version: 0.0.2
Summary: Python package to generate 2D and 3D images using Generative Adversarial Networks and PyTorch
Author: Guillaume Rongier
License-Expression: MIT
Project-URL: Homepage, https://github.com/grongier/voxgan
Project-URL: Bug Tracker, https://github.com/grongier/voxgan/issues
Keywords: python,deep learning,deep generative modeling,GAN,2D,3D,PyTorch
Classifier: Intended Audience :: Science/Research
Classifier: Topic :: Scientific/Engineering
Classifier: Development Status :: 4 - Beta
Classifier: Natural Language :: English
Classifier: Programming Language :: Python :: 3.9
Classifier: Programming Language :: Python :: 3.10
Classifier: Programming Language :: Python :: 3.11
Classifier: Programming Language :: Python :: 3.12
Classifier: Operating System :: OS Independent
Requires-Python: >=3.9
License-File: LICENSE
Requires-Dist: numpy<2.0
Requires-Dist: scipy
Requires-Dist: h5py
Requires-Dist: torch
Requires-Dist: scikit-learn
Requires-Dist: bottleneck
Dynamic: license-file
